delete/__init__.py
delete/main.py
delete/realLife__1.py
delete/server.py
delete/setting__1.py
delete/status.py
delete/task_func__1.py
delete/task_manager__1.py
delete/tasks.py
delete/utils.py
reallife/__init__.py
reallife/abstra.py
reallife/cli.py
reallife/execution_strategy.py
reallife/log.py
reallife/server.py
reallife/task_manager.py
reallife/task_state.py
reallife/workday_facade.py
reallife/workday_tasks.yaml
reallife/workday_tasks_new.yaml
reallife-0.3.12.dist-info/METADATA
reallife-0.3.12.dist-info/WHEEL
reallife-0.3.12.dist-info/top_level.txt
reallife-0.3.12.dist-info/RECORD
