Metadata-Version: 2.4
Name: reallife
Version: 0.3.12
Summary: 客服端服务端
Requires-Python: >=3.10
Requires-Dist: apscheduler>=3.11.0
Requires-Dist: fastapi>=0.115.12
Requires-Dist: pyyaml>=6.0.2
Requires-Dist: toml==0.10.2
Provides-Extra: extra
Requires-Dist: appscriptz>=0.1.4; extra == "extra"
Requires-Dist: chinese-calendar>=1.10.0; extra == "extra"
Requires-Dist: grapherz>=0.1.5; extra == "extra"
Requires-Dist: kanbanz>=0.2.0; extra == "extra"
Requires-Dist: llmada==0.1.11; extra == "extra"
Requires-Dist: numpy>=2.2.5; extra == "extra"
Requires-Dist: pandas>=2.2.3; extra == "extra"
Requires-Dist: promptlibz>=0.2.1; extra == "extra"
Requires-Dist: toolsz==1.0.1; extra == "extra"
